qibb/HyperparameterUtil.py
qibb/__init__.py
qibb/ioUtil.py
qibb/mlModelLoggingUtil.py
qibb/s3ioUtil.py
qibb-0.0.1.dist-info/METADATA
qibb-0.0.1.dist-info/WHEEL
qibb-0.0.1.dist-info/top_level.txt
qibb-0.0.1.dist-info/RECORD
