Metadata-Version: 2.1
Name: qibb
Version: 0.0.1
Summary: qibb commons
Home-page: UNKNOWN
Author: Himanshu
Author-email: <himanshu.gju@gmail.com>
License: UNKNOWN
Keywords: qibb
Platform: UNKNOWN
Classifier: Development Status :: 1 - Planning
Classifier: Intended Audience :: Developers
Classifier: Programming Language :: Python :: 3
Classifier: Operating System :: Unix
Classifier: Operating System :: MacOS :: MacOS X
Classifier: Operating System :: Microsoft :: Windows
Requires-Dist: boto3
